pyusbpd/__init__.py
pyusbpd/enum.py
pyusbpd/message.py
pyusbpd-0.0.1.dist-info/LICENSE
pyusbpd-0.0.1.dist-info/METADATA
pyusbpd-0.0.1.dist-info/WHEEL
pyusbpd-0.0.1.dist-info/top_level.txt
pyusbpd-0.0.1.dist-info/RECORD
