Metadata-Version: 2.1
Name: pyusbpd
Version: 0.0.1
Summary: Unofficial USB Power Delivery toolbox for Python
Author: Jean THOMAS
Author-email: virgule@jeanthomas.me
License: ISC
Requires-Python: >=3.8
License-File: LICENSE
